banker_projection_model/__init__.py
banker_projection_model/abstracted_packages.py
banker_projection_model/saving_model/__init__.py
banker_projection_model/saving_model/quarterly_projected_result.py
banker_projection_model/saving_model/saving_full_workflow.py
banker_projection_model/saving_model/saving_model_proj.py
banker_projection_model/saving_model/_1_input_data_manager/__init__.py
banker_projection_model/saving_model/_1_input_data_manager/data_aggregate.py
banker_projection_model/saving_model/_1_input_data_manager/merge_all_tables.py
banker_projection_model/saving_model/_1_input_data_manager/model_point_generator.py
banker_projection_model/saving_model/_2_undisc_cf_projector/__init__.py
banker_projection_model/saving_model/_2_undisc_cf_projector/run_saving.py
banker_projection_model/saving_model/_2_undisc_cf_projector/validator_dfs.py
banker_projection_model/saving_model/_2_undisc_cf_projector/saving/_1_duration.py
banker_projection_model/saving_model/_2_undisc_cf_projector/saving/_2_reserve.py
banker_projection_model/saving_model/_2_undisc_cf_projector/saving/_3_proba.py
banker_projection_model/saving_model/_2_undisc_cf_projector/saving/_4_prospective.py
banker_projection_model/saving_model/_2_undisc_cf_projector/saving/__init__.py
banker_projection_model/saving_model/_2_undisc_cf_projector/saving/required_data_calculation.py
banker_projection_model/term_life/__init__.py
config/__init__.py
inputs/__init__.py
almas_bankers-0.0.5.dist-info/METADATA
almas_bankers-0.0.5.dist-info/WHEEL
almas_bankers-0.0.5.dist-info/top_level.txt
almas_bankers-0.0.5.dist-info/RECORD
