Metadata-Version: 2.1
Name: almas-bankers
Version: 0.0.5
Summary: bankers-modules
Author: Novacture
Author-email: amine.zemni@novacture.com
Classifier: Programming Language :: Python :: 3
Requires-Dist: numpy
Requires-Dist: pandas ==2.2.2
Requires-Dist: pytest
